{
  "project_info": {
    "project_number": "389218904653",
    "project_id": "sw-project-53154",
    "storage_bucket": "sw-project-53154.appspot.com"
  },
  "client": [
    {
      "client_info": {
        "mobilesdk_app_id": "1:389218904653:android:d6335bbc62d55a27c70a04",
        "android_client_info": {
          "package_name": "com.example.practice"
        }
      },
      "oauth_client": [
        {
          "client_id": "389218904653-16cffa70vcvgmn4v1kdib589i5172qgb.apps.googleusercontent.com",
          "client_type": 3
        }
      ],
      "api_key": [
        {
          "current_key": "AIzaSyDS9J-IenuzW6_kVTXt3OZsgumU3JJJHp4"
        }
      ],
      "services": {
        "appinvite_service": {
          "other_platform_oauth_client": [
            {
              "client_id": "389218904653-16cffa70vcvgmn4v1kdib589i5172qgb.apps.googleusercontent.com",
              "client_type": 3
            }
          ]
        }
      }
    }
  ],
  "configuration_version": "1"
}